hackinfo.py
hackinfo-1.1.0.dist-info/WHEEL
hackinfo-1.1.0.dist-info/METADATA
hackinfo-1.1.0.dist-info/RECORD
