Metadata-Version: 2.1
Name: hackinfo
Version: 1.1.0
Summary: web application Hejab Zaeri
Home-page: https://github.com/Matrix07ksa/HackerInfo
License: GPL-3.0
Author: Hejab Zaeri
Requires-Python: >=3.7,<4.0
Classifier: License :: OSI Approved :: GNU General Public License v3 (GPLv3)
Classifier: Programming Language :: Python :: 3
Classifier: Programming Language :: Python :: 3.7
